[
  {
    "_id": "5e699b1fb67a735204880f2d",
    "index": 0,
    "name": {
      "first": "Roberta",
      "last": "Horton"
    },
    "email": "roberta.horton@undefined.biz",
    "greeting": "Hello, Roberta! You have 7 unread messages."
  },
  {
    "_id": "5e699b1f400d8b2dae6cada6",
    "index": 1,
    "name": {
      "first": "Jenna",
      "last": "Carney"
    },
    "email": "jenna.carney@undefined.name",
    "greeting": "Hello, Jenna! You have 9 unread messages."
  },
  {
    "_id": "5e699b1f517f2b17efa944f9",
    "index": 2,
    "name": {
      "first": "Tia",
      "last": "Harrison"
    },
    "email": "tia.harrison@undefined.co.uk",
    "greeting": "Hello, Tia! You have 8 unread messages."
  },
  {
    "_id": "5e699b1fc601a5e6418003d0",
    "index": 3,
    "name": {
      "first": "Ida",
      "last": "Shelton"
    },
    "email": "ida.shelton@undefined.biz",
    "greeting": "Hello, Ida! You have 5 unread messages."
  },
  {
    "_id": "5e699b1f3b2e468fd47c82c0",
    "index": 4,
    "name": {
      "first": "Nunez",
      "last": "Sharpe"
    },
    "email": "nunez.sharpe@undefined.me",
    "greeting": "Hello, Nunez! You have 5 unread messages."
  }
]